escheduler_sdk/__init__.py
escheduler_sdk/client.py
escheduler_sdk/exceptions.py
escheduler_sdk/models.py
escheduler_sdk/scheduler.py
escheduler_sdk/sdk.py
escheduler_sdk/team.py
escheduler_sdk-0.0.2.dist-info/licenses/LICENSE
escheduler_sdk-0.0.2.dist-info/METADATA
escheduler_sdk-0.0.2.dist-info/WHEEL
escheduler_sdk-0.0.2.dist-info/top_level.txt
escheduler_sdk-0.0.2.dist-info/RECORD
